{
  "name": "component_8",
  "version": 32,
  "source-key": {
    "type": "figma",
    "file": "knsA6gRCysCuUCz1aMSZEZ",
    "node": "102:131",
    "version": "3134442840",
    "component-id": "4c22d89d12124d9876311de358ff189083b15552"
  },
  "default": "Component 8",
  "documentation": "Leaderboard\n\n",
  "design": {
    "atoms": [
      {
        "type": "group",
        "id": "top_level",
        "root": "true"
      },
      {
        "type": "text",
        "id": "Text"
      },
      {
        "type": "text",
        "id": "Patricia Edwards"
      },
      {
        "type": "text",
        "id": "John Doe"
      },
      {
        "type": "vector",
        "id": "Line 2"
      },
      {
        "type": "vector",
        "id": "Line 3"
      },
      {
        "type": "group",
        "id": "Ellipse 2"
      },
      {
        "type": "group",
        "id": "Ellipse 7"
      },
      {
        "type": "vector",
        "id": "Ellipse 3"
      },
      {
        "type": "vector",
        "id": "Ellipse 4"
      },
      {
        "type": "vector",
        "id": "Ellipse 5"
      },
      {
        "type": "text",
        "id": "339 points"
      },
      {
        "type": "text",
        "id": "250 points"
      },
      {
        "type": "text",
        "id": "223 points"
      },
      {
        "type": "text",
        "id": "196 points"
      },
      {
        "type": "text",
        "id": "1."
      },
      {
        "type": "text",
        "id": "2."
      },
      {
        "type": "text",
        "id": "3."
      },
      {
        "type": "text",
        "id": "4."
      },
      {
        "type": "text",
        "id": "Eddy Murphy"
      },
      {
        "type": "text",
        "id": "Cash Stewart"
      },
      {
        "type": "group",
        "id": "Frame"
      },
      {
        "type": "group",
        "id": "Frame1"
      },
      {
        "type": "group",
        "id": "Frame2"
      },
      {
        "type": "vector",
        "id": "Rectangle 5"
      },
      {
        "type": "vector",
        "id": "Polygon 1"
      },
      {
        "type": "text",
        "id": "Leaderboard"
      },
      {
        "type": "image",
        "id": "logo 3"
      },
      {
        "type": "group",
        "id": "Ellipse 6"
      },
      {
        "type": "image",
        "id": "setting 1"
      },
      {
        "type": "vector",
        "id": "Ellipse 8"
      },
      {
        "type": "group",
        "id": "Frame3"
      },
      {
        "type": "vector",
        "id": "Vector"
      },
      {
        "type": "vector",
        "id": "Vector1"
      },
      {
        "type": "vector",
        "id": "Vector2"
      },
      {
        "type": "group",
        "id": "Group"
      },
      {
        "type": "vector",
        "id": "Vector3"
      },
      {
        "type": "vector",
        "id": "Vector4"
      },
      {
        "type": "vector",
        "id": "Vector5"
      },
      {
        "type": "vector",
        "id": "Vector6"
      },
      {
        "type": "vector",
        "id": "Ellipse 9"
      },
      {
        "type": "group",
        "id": "Frame4"
      },
      {
        "type": "vector",
        "id": "Vector7"
      },
      {
        "type": "vector",
        "id": "Vector8"
      },
      {
        "type": "vector",
        "id": "Vector9"
      },
      {
        "type": "group",
        "id": "Group1"
      },
      {
        "type": "vector",
        "id": "Vector10"
      },
      {
        "type": "vector",
        "id": "Vector11"
      },
      {
        "type": "vector",
        "id": "Vector12"
      },
      {
        "type": "vector",
        "id": "Vector13"
      },
      {
        "type": "group",
        "id": "Group2"
      },
      {
        "type": "vector",
        "id": "Vector14"
      },
      {
        "type": "vector",
        "id": "Vector15"
      },
      {
        "type": "vector",
        "id": "Vector16"
      },
      {
        "type": "vector",
        "id": "Vector17"
      },
      {
        "type": "vector",
        "id": "Vector18"
      },
      {
        "type": "vector",
        "id": "Vector19"
      },
      {
        "type": "vector",
        "id": "Vector20"
      },
      {
        "type": "vector",
        "id": "Vector21"
      },
      {
        "type": "vector",
        "id": "Vector22"
      },
      {
        "type": "group",
        "id": "Group3"
      },
      {
        "type": "vector",
        "id": "Vector23"
      },
      {
        "type": "vector",
        "id": "Vector24"
      },
      {
        "type": "vector",
        "id": "Vector25"
      },
      {
        "type": "vector",
        "id": "Vector26"
      },
      {
        "type": "vector",
        "id": "Vector27"
      },
      {
        "type": "vector",
        "id": "Vector28"
      },
      {
        "type": "vector",
        "id": "Vector29"
      },
      {
        "type": "vector",
        "id": "Vector30"
      },
      {
        "type": "vector",
        "id": "Vector31"
      },
      {
        "type": "vector",
        "id": "Vector32"
      },
      {
        "type": "vector",
        "id": "Vector33"
      },
      {
        "type": "vector",
        "id": "Ellipse 10"
      },
      {
        "type": "group",
        "id": "Frame5"
      },
      {
        "type": "vector",
        "id": "Vector34"
      },
      {
        "type": "vector",
        "id": "Vector35"
      },
      {
        "type": "vector",
        "id": "Vector36"
      },
      {
        "type": "group",
        "id": "Group4"
      },
      {
        "type": "vector",
        "id": "Vector37"
      },
      {
        "type": "vector",
        "id": "Vector38"
      },
      {
        "type": "vector",
        "id": "Vector39"
      },
      {
        "type": "vector",
        "id": "Vector40"
      }
    ],
    "modes": {
      "Component 8": {
        "rules": [
          {
            "id": "top_level",
            "is-structured": "false",
            "children": [
              "Text",
              "Patricia Edwards",
              "John Doe",
              "Line 2",
              "Line 3",
              "Ellipse 2",
              "Ellipse 7",
              "Ellipse 3",
              "Ellipse 4",
              "Ellipse 5",
              "339 points",
              "250 points",
              "223 points",
              "196 points",
              "1.",
              "2.",
              "3.",
              "4.",
              "Eddy Murphy",
              "Cash Stewart",
              "Frame",
              "Frame1",
              "Frame2",
              "Rectangle 5",
              "Polygon 1",
              "Leaderboard",
              "logo 3",
              "Ellipse 6",
              "setting 1"
            ],
            "clip-content": "false"
          },
          {
            "id": "Text",
            "margin": {
              "left": "110.0",
              "top": "193.0",
              "right": "253.9998779296875",
              "bottom": "378.0"
            },
            "size-constraints": {
              "width-constraints": {
                "sizing-mode": "proportional",
                "value": "1.0"
              },
              "height-constraints": {
                "sizing-mode": "proportional",
                "value": "1.0"
              }
            },
            "color": {
              "alpha": "1.0",
              "hue": "0.0",
              "saturation": "0.0",
              "value": "0.0"
            },
            "text-content": "",
            "overflow": "visible",
            "text-align": "left",
            "text-size": "12.0",
            "line-height": "1.2102272510528564",
            "typeface": "Inter"
          },
          {
            "id": "Patricia Edwards",
            "margin": {
              "left": "128.0",
              "top": "287.0",
              "right": "103.9998779296875",
              "bottom": "280.0"
            },
            "size-constraints": {
              "width-constraints": {
                "sizing-mode": "proportional",
                "value": "1.0"
              },
              "height-constraints": {
                "sizing-mode": "proportional",
                "value": "1.0"
              }
            },
            "font-weight": "700.0",
            "color": {
              "alpha": "1.0",
              "hue": "0.0",
              "saturation": "0.0",
              "value": "0.24313725490196078"
            },
            "text-content": "Patricia Edwards",
            "overflow": "visible",
            "text-align": "left",
            "text-size": "16.0",
            "line-height": "1.2102272510528564",
            "typeface": "Inter"
          },
          {
            "id": "John Doe",
            "margin": {
              "left": "154.0",
              "top": "187.0",
              "right": "115.9998779296875",
              "bottom": "375.0"
            },
            "size-constraints": {
              "width-constraints": {
                "sizing-mode": "proportional",
                "value": "1.0"
              },
              "height-constraints": {
                "sizing-mode": "proportional",
                "value": "1.0"
              }
            },
            "font-weight": "900.0",
            "color": {
              "alpha": "1.0",
              "hue": "0.0",
              "saturation": "0.0",
              "value": "0.24313725490196078"
            },
            "text-content": "John Doe",
            "overflow": "visible",
            "text-align": "left",
            "text-size": "20.0",
            "line-height": "1.2102272033691406",
            "typeface": "Inter"
          },
          {
            "id": "Line 2",
            "margin": {
              "top": "69.52312116870478",
              "right": "1.9992598323860875",
              "bottom": "516.4768788312953"
            },
            "size-constraints": {
              "width-constraints": {
                "sizing-mode": "proportional",
                "value": "1.0"
              },
              "height-constraints": {
                "sizing-mode": "proportional",
                "value": "1.0"
              }
            },
            "vector-content": "line_2.svg"
          },
          {
            "id": "Line 3",
            "margin": {
              "left": "1.9992448062857875",
              "top": "530.5231211687047",
              "bottom": "55.47687883129527"
            },
            "size-constraints": {
              "width-constraints": {
                "sizing-mode": "proportional",
                "value": "1.0"
              },
              "height-constraints": {
                "sizing-mode": "proportional",
                "value": "1.0"
              }
            },
            "vector-content": "line_3.svg"
          },
          {
            "id": "Ellipse 2",
            "margin": {
              "left": "59.0",
              "top": "174.0",
              "right": "235.9998779296875",
              "bottom": "343.0"
            },
            "is-structured": "false",
            "children": [
              "Ellipse 8",
              "Frame3"
            ],
            "clip-content": "false"
          },
          {
            "id": "Ellipse 7",
            "margin": {
              "left": "59.0",
              "top": "174.0",
              "right": "235.9998779296875",
              "bottom": "343.0"
            },
            "is-structured": "false",
            "children": [
              "Ellipse 9",
              "Frame4"
            ],
            "clip-content": "false"
          },
          {
            "id": "Ellipse 3",
            "margin": {
              "left": "52.0",
              "top": "276.0",
              "right": "257.9998779296875",
              "bottom": "256.0"
            },
            "size-constraints": {
              "width-constraints": {
                "sizing-mode": "proportional",
                "value": "1.0"
              },
              "height-constraints": {
                "sizing-mode": "proportional",
                "value": "1.0"
              }
            },
            "vector-content": "ellipse_3.svg"
          },
          {
            "id": "Ellipse 4",
            "margin": {
              "left": "52.0",
              "top": "347.0",
              "right": "257.9998779296875",
              "bottom": "185.0"
            },
            "size-constraints": {
              "width-constraints": {
                "sizing-mode": "proportional",
                "value": "1.0"
              },
              "height-constraints": {
                "sizing-mode": "proportional",
                "value": "1.0"
              }
            },
            "vector-content": "ellipse_4.svg"
          },
          {
            "id": "Ellipse 5",
            "margin": {
              "left": "52.0",
              "top": "418.0",
              "right": "257.9998779296875",
              "bottom": "114.0"
            },
            "size-constraints": {
              "width-constraints": {
                "sizing-mode": "proportional",
                "value": "1.0"
              },
              "height-constraints": {
                "sizing-mode": "proportional",
                "value": "1.0"
              }
            },
            "vector-content": "ellipse_5.svg"
          },
          {
            "id": "339 points",
            "margin": {
              "left": "154.0",
              "top": "212.0",
              "right": "148.9998779296875",
              "bottom": "359.0"
            },
            "size-constraints": {
              "width-constraints": {
                "sizing-mode": "proportional",
                "value": "1.0"
              },
              "height-constraints": {
                "sizing-mode": "proportional",
                "value": "1.0"
              }
            },
            "color": {
              "alpha": "1.0",
              "hue": "29.24050632911392",
              "saturation": "0.696035242290749",
              "value": "0.8901960784313725"
            },
            "text-content": "339 points",
            "overflow": "visible",
            "text-align": "left",
            "text-size": "12.0",
            "line-height": "1.2102272510528564",
            "typeface": "Inter"
          },
          {
            "id": "250 points",
            "margin": {
              "left": "128.0",
              "top": "306.0",
              "right": "184.9998779296875",
              "bottom": "268.0"
            },
            "size-constraints": {
              "width-constraints": {
                "sizing-mode": "proportional",
                "value": "1.0"
              },
              "height-constraints": {
                "sizing-mode": "proportional",
                "value": "1.0"
              }
            },
            "color": {
              "alpha": "1.0",
              "hue": "29.24050632911392",
              "saturation": "0.696035242290749",
              "value": "0.8901960784313725"
            },
            "text-content": "250 points",
            "overflow": "visible",
            "text-align": "left",
            "text-size": "10.0",
            "line-height": "1.2102272033691406",
            "typeface": "Inter"
          },
          {
            "id": "223 points",
            "margin": {
              "left": "128.0",
              "top": "378.0",
              "right": "184.9998779296875",
              "bottom": "196.0"
            },
            "size-constraints": {
              "width-constraints": {
                "sizing-mode": "proportional",
                "value": "1.0"
              },
              "height-constraints": {
                "sizing-mode": "proportional",
                "value": "1.0"
              }
            },
            "color": {
              "alpha": "1.0",
              "hue": "29.24050632911392",
              "saturation": "0.696035242290749",
              "value": "0.8901960784313725"
            },
            "text-content": "223 points",
            "overflow": "visible",
            "text-align": "left",
            "text-size": "10.0",
            "line-height": "1.2102272033691406",
            "typeface": "Inter"
          },
          {
            "id": "196 points",
            "margin": {
              "left": "128.0",
              "top": "448.0",
              "right": "186.9998779296875",
              "bottom": "126.0"
            },
            "size-constraints": {
              "width-constraints": {
                "sizing-mode": "proportional",
                "value": "1.0"
              },
              "height-constraints": {
                "sizing-mode": "proportional",
                "value": "1.0"
              }
            },
            "color": {
              "alpha": "1.0",
              "hue": "29.24050632911392",
              "saturation": "0.696035242290749",
              "value": "0.8901960784313725"
            },
            "text-content": "196 points",
            "overflow": "visible",
            "text-align": "left",
            "text-size": "10.0",
            "line-height": "1.2102272033691406",
            "typeface": "Inter"
          },
          {
            "id": "1.",
            "margin": {
              "left": "26.0",
              "top": "187.0",
              "right": "314.9998779296875",
              "bottom": "360.0"
            },
            "size-constraints": {
              "width-constraints": {
                "sizing-mode": "proportional",
                "value": "1.0"
              },
              "height-constraints": {
                "sizing-mode": "proportional",
                "value": "1.0"
              }
            },
            "color": {
              "alpha": "1.0",
              "hue": "29.24050632911392",
              "saturation": "0.696035242290749",
              "value": "0.8901960784313725"
            },
            "text-content": "1.",
            "overflow": "visible",
            "text-align": "left",
            "text-size": "32.0",
            "line-height": "1.2102272510528564",
            "typeface": "Inter"
          },
          {
            "id": "2.",
            "margin": {
              "left": "13.0",
              "top": "286.0",
              "right": "332.9998779296875",
              "bottom": "276.0"
            },
            "size-constraints": {
              "width-constraints": {
                "sizing-mode": "proportional",
                "value": "1.0"
              },
              "height-constraints": {
                "sizing-mode": "proportional",
                "value": "1.0"
              }
            },
            "color": {
              "alpha": "1.0",
              "hue": "29.24050632911392",
              "saturation": "0.696035242290749",
              "value": "0.8901960784313725"
            },
            "text-content": "2.",
            "overflow": "visible",
            "text-align": "left",
            "text-size": "20.0",
            "line-height": "1.2102272033691406",
            "typeface": "Inter"
          },
          {
            "id": "3.",
            "margin": {
              "left": "28.0",
              "top": "362.0",
              "right": "317.9998779296875",
              "bottom": "200.0"
            },
            "size-constraints": {
              "width-constraints": {
                "sizing-mode": "proportional",
                "value": "1.0"
              },
              "height-constraints": {
                "sizing-mode": "proportional",
                "value": "1.0"
              }
            },
            "color": {
              "alpha": "1.0",
              "hue": "29.24050632911392",
              "saturation": "0.696035242290749",
              "value": "0.8901960784313725"
            },
            "text-content": "3.",
            "overflow": "visible",
            "text-align": "left",
            "text-size": "20.0",
            "line-height": "1.2102272033691406",
            "typeface": "Inter"
          },
          {
            "id": "4.",
            "margin": {
              "left": "13.0",
              "top": "432.0",
              "right": "332.9998779296875",
              "bottom": "130.0"
            },
            "size-constraints": {
              "width-constraints": {
                "sizing-mode": "proportional",
                "value": "1.0"
              },
              "height-constraints": {
                "sizing-mode": "proportional",
                "value": "1.0"
              }
            },
            "color": {
              "alpha": "1.0",
              "hue": "29.24050632911392",
              "saturation": "0.696035242290749",
              "value": "0.8901960784313725"
            },
            "text-content": "4.",
            "overflow": "visible",
            "text-align": "left",
            "text-size": "20.0",
            "line-height": "1.2102272033691406",
            "typeface": "Inter"
          },
          {
            "id": "Eddy Murphy",
            "margin": {
              "left": "128.0",
              "top": "359.0",
              "right": "131.9998779296875",
              "bottom": "208.0"
            },
            "size-constraints": {
              "width-constraints": {
                "sizing-mode": "proportional",
                "value": "1.0"
              },
              "height-constraints": {
                "sizing-mode": "proportional",
                "value": "1.0"
              }
            },
            "font-weight": "700.0",
            "color": {
              "alpha": "1.0",
              "hue": "0.0",
              "saturation": "0.0",
              "value": "0.24313725490196078"
            },
            "text-content": "Eddy Murphy",
            "overflow": "visible",
            "text-align": "left",
            "text-size": "16.0",
            "line-height": "1.2102272510528564",
            "typeface": "Inter"
          },
          {
            "id": "Cash Stewart",
            "margin": {
              "left": "128.0",
              "top": "429.0",
              "right": "128.9998779296875",
              "bottom": "138.0"
            },
            "size-constraints": {
              "width-constraints": {
                "sizing-mode": "proportional",
                "value": "1.0"
              },
              "height-constraints": {
                "sizing-mode": "proportional",
                "value": "1.0"
              }
            },
            "font-weight": "700.0",
            "color": {
              "alpha": "1.0",
              "hue": "0.0",
              "saturation": "0.0",
              "value": "0.24313725490196078"
            },
            "text-content": "Cash Stewart",
            "overflow": "visible",
            "text-align": "left",
            "text-size": "16.0",
            "line-height": "1.2102272510528564",
            "typeface": "Inter"
          },
          {
            "id": "Frame",
            "margin": {
              "left": "66.0",
              "top": "283.0",
              "right": "268.9998779296875",
              "bottom": "264.0"
            },
            "is-structured": "false",
            "children": [
              "Group2"
            ]
          },
          {
            "id": "Frame1",
            "margin": {
              "left": "70.0",
              "top": "358.0",
              "right": "275.9998779296875",
              "bottom": "196.0"
            },
            "is-structured": "false",
            "children": [
              "Vector22",
              "Group3"
            ]
          },
          {
            "id": "Frame2",
            "margin": {
              "left": "70.0",
              "top": "430.0",
              "right": "271.9998779296875",
              "bottom": "126.0"
            },
            "is-structured": "false",
            "children": [
              "Vector28",
              "Vector29",
              "Vector30",
              "Vector31",
              "Vector32",
              "Vector33"
            ]
          },
          {
            "id": "Rectangle 5",
            "margin": {
              "left": "46.0",
              "top": "553.0",
              "right": "285.9998779296875"
            },
            "size-constraints": {
              "width-constraints": {
                "sizing-mode": "proportional",
                "value": "1.0"
              },
              "height-constraints": {
                "sizing-mode": "proportional",
                "value": "1.0"
              }
            },
            "vector-content": "rectangle_5.svg"
          },
          {
            "id": "Polygon 1",
            "margin": {
              "left": "35.0",
              "top": "535.0",
              "right": "274.9998779296875",
              "bottom": "16.0"
            },
            "size-constraints": {
              "width-constraints": {
                "sizing-mode": "proportional",
                "value": "1.0"
              },
              "height-constraints": {
                "sizing-mode": "proportional",
                "value": "1.0"
              }
            },
            "vector-content": "polygon_1.svg"
          },
          {
            "id": "Leaderboard",
            "margin": {
              "left": "69.0",
              "top": "100.0",
              "right": "69.9998779296875",
              "bottom": "442.0"
            },
            "size-constraints": {
              "width-constraints": {
                "sizing-mode": "proportional",
                "value": "1.0"
              },
              "height-constraints": {
                "sizing-mode": "proportional",
                "value": "1.0"
              }
            },
            "font-weight": "700.0",
            "color": {
              "alpha": "1.0",
              "hue": "0.0",
              "saturation": "0.0",
              "value": "0.24313725490196078"
            },
            "text-content": "Leaderboard",
            "overflow": "visible",
            "text-align": "left",
            "text-size": "36.0",
            "line-height": "1.2102272245619032",
            "typeface": "Inter"
          },
          {
            "id": "logo 3",
            "margin": {
              "left": "123.0",
              "top": "9.0",
              "right": "100.9998779296875",
              "bottom": "546.0"
            },
            "size-constraints": {
              "width-constraints": {
                "sizing-mode": "proportional",
                "value": "1.0"
              },
              "height-constraints": {
                "sizing-mode": "proportional",
                "value": "1.0"
              }
            },
            "image-content": "logo_3.png",
            "scale": "cover"
          },
          {
            "id": "Ellipse 6",
            "margin": {
              "left": "23.0",
              "right": "290.9998779296875",
              "bottom": "536.0"
            },
            "is-structured": "false",
            "children": [
              "Ellipse 10",
              "Frame5"
            ],
            "clip-content": "false"
          },
          {
            "id": "setting 1",
            "margin": {
              "left": "313.0",
              "top": "11.0",
              "right": "22.9998779296875",
              "bottom": "547.0"
            },
            "size-constraints": {
              "width-constraints": {
                "sizing-mode": "proportional",
                "value": "1.0"
              },
              "height-constraints": {
                "sizing-mode": "proportional",
                "value": "1.0"
              }
            },
            "image-content": "setting_1.png",
            "scale": "cover"
          },
          {
            "id": "Ellipse 8",
            "size-constraints": {
              "width-constraints": {
                "sizing-mode": "proportional",
                "value": "1.0"
              },
              "height-constraints": {
                "sizing-mode": "proportional",
                "value": "1.0"
              }
            },
            "vector-content": "ellipse_2.svg"
          },
          {
            "id": "Frame3",
            "margin": {
              "left": "14.980262756347656",
              "top": "6.809211730957031",
              "right": "14.812301635742188",
              "bottom": "7.0407257080078125"
            },
            "is-structured": "false",
            "children": [
              "Vector",
              "Vector1",
              "Vector2",
              "Group",
              "Vector3"
            ]
          },
          {
            "id": "Vector",
            "margin": {
              "left": "5.1931610107421875",
              "top": "29.372451782226562"
            },
            "size-constraints": {
              "width-constraints": {
                "sizing-mode": "proportional",
                "value": "1.0"
              },
              "height-constraints": {
                "sizing-mode": "proportional",
                "value": "1.0"
              }
            },
            "vector-content": "vector.svg"
          },
          {
            "id": "Vector1",
            "margin": {
              "left": "19.388092041015625",
              "top": "20.184463500976562",
              "right": "10.640403747558594",
              "bottom": "19.55992889404297"
            },
            "size-constraints": {
              "width-constraints": {
                "sizing-mode": "proportional",
                "value": "1.0"
              },
              "height-constraints": {
                "sizing-mode": "proportional",
                "value": "1.0"
              }
            },
            "vector-content": "vector1.svg"
          },
          {
            "id": "Vector2",
            "margin": {
              "left": "20.650062561035156",
              "top": "20.182571411132812",
              "right": "11.480331420898438",
              "bottom": "29.51111602783203"
            },
            "size-constraints": {
              "width-constraints": {
                "sizing-mode": "proportional",
                "value": "1.0"
              },
              "height-constraints": {
                "sizing-mode": "proportional",
                "value": "1.0"
              }
            },
            "vector-content": "vector2.svg"
          },
          {
            "id": "Group",
            "margin": {
              "left": "13.81488037109375",
              "right": "7.322242736816406",
              "bottom": "30.9637451171875"
            },
            "is-structured": "false",
            "children": [
              "Vector4",
              "Vector5",
              "Vector6"
            ],
            "clip-content": "false"
          },
          {
            "id": "Vector3",
            "margin": {
              "top": "31.569557189941406",
              "right": "24.35601043701172",
              "bottom": "2.6419677734375"
            },
            "size-constraints": {
              "width-constraints": {
                "sizing-mode": "proportional",
                "value": "1.0"
              },
              "height-constraints": {
                "sizing-mode": "proportional",
                "value": "1.0"
              }
            },
            "vector-content": "vector3.svg"
          },
          {
            "id": "Vector4",
            "margin": {
              "left": "5.2165679931640625",
              "top": "4.7690277099609375",
              "bottom": "0.2305755615234375"
            },
            "size-constraints": {
              "width-constraints": {
                "sizing-mode": "proportional",
                "value": "1.0"
              },
              "height-constraints": {
                "sizing-mode": "proportional",
                "value": "1.0"
              }
            },
            "vector-content": "vector4.svg"
          },
          {
            "id": "Vector5",
            "margin": {
              "right": "1.5063705444335938"
            },
            "size-constraints": {
              "width-constraints": {
                "sizing-mode": "proportional",
                "value": "1.0"
              },
              "height-constraints": {
                "sizing-mode": "proportional",
                "value": "1.0"
              }
            },
            "vector-content": "vector5.svg"
          },
          {
            "id": "Vector6",
            "margin": {
              "left": "6.121849060058594",
              "top": "13.347412109375",
              "right": "9.246208190917969",
              "bottom": "6.155387878417969"
            },
            "size-constraints": {
              "width-constraints": {
                "sizing-mode": "proportional",
                "value": "1.0"
              },
              "height-constraints": {
                "sizing-mode": "proportional",
                "value": "1.0"
              }
            },
            "vector-content": "vector6.svg"
          },
          {
            "id": "Ellipse 9",
            "size-constraints": {
              "width-constraints": {
                "sizing-mode": "proportional",
                "value": "1.0"
              },
              "height-constraints": {
                "sizing-mode": "proportional",
                "value": "1.0"
              }
            },
            "vector-content": "ellipse_6.svg"
          },
          {
            "id": "Frame4",
            "margin": {
              "left": "14.980262756347656",
              "top": "6.809211730957031",
              "right": "14.812301635742188",
              "bottom": "7.0407257080078125"
            },
            "is-structured": "false",
            "children": [
              "Vector7",
              "Vector8",
              "Vector9",
              "Group1",
              "Vector10"
            ]
          },
          {
            "id": "Vector7",
            "margin": {
              "left": "5.1931610107421875",
              "top": "29.372451782226562"
            },
            "size-constraints": {
              "width-constraints": {
                "sizing-mode": "proportional",
                "value": "1.0"
              },
              "height-constraints": {
                "sizing-mode": "proportional",
                "value": "1.0"
              }
            },
            "vector-content": "vector7.svg"
          },
          {
            "id": "Vector8",
            "margin": {
              "left": "19.388092041015625",
              "top": "20.184463500976562",
              "right": "10.640403747558594",
              "bottom": "19.55992889404297"
            },
            "size-constraints": {
              "width-constraints": {
                "sizing-mode": "proportional",
                "value": "1.0"
              },
              "height-constraints": {
                "sizing-mode": "proportional",
                "value": "1.0"
              }
            },
            "vector-content": "vector8.svg"
          },
          {
            "id": "Vector9",
            "margin": {
              "left": "20.650062561035156",
              "top": "20.182571411132812",
              "right": "11.480331420898438",
              "bottom": "29.51111602783203"
            },
            "size-constraints": {
              "width-constraints": {
                "sizing-mode": "proportional",
                "value": "1.0"
              },
              "height-constraints": {
                "sizing-mode": "proportional",
                "value": "1.0"
              }
            },
            "vector-content": "vector9.svg"
          },
          {
            "id": "Group1",
            "margin": {
              "left": "13.81488037109375",
              "right": "7.322242736816406",
              "bottom": "30.9637451171875"
            },
            "is-structured": "false",
            "children": [
              "Vector11",
              "Vector12",
              "Vector13"
            ],
            "clip-content": "false"
          },
          {
            "id": "Vector10",
            "margin": {
              "top": "31.569557189941406",
              "right": "24.35601043701172",
              "bottom": "2.6419677734375"
            },
            "size-constraints": {
              "width-constraints": {
                "sizing-mode": "proportional",
                "value": "1.0"
              },
              "height-constraints": {
                "sizing-mode": "proportional",
                "value": "1.0"
              }
            },
            "vector-content": "vector10.svg"
          },
          {
            "id": "Vector11",
            "margin": {
              "left": "5.2165679931640625",
              "top": "4.7690277099609375",
              "bottom": "0.2305755615234375"
            },
            "size-constraints": {
              "width-constraints": {
                "sizing-mode": "proportional",
                "value": "1.0"
              },
              "height-constraints": {
                "sizing-mode": "proportional",
                "value": "1.0"
              }
            },
            "vector-content": "vector11.svg"
          },
          {
            "id": "Vector12",
            "margin": {
              "right": "1.5063705444335938"
            },
            "size-constraints": {
              "width-constraints": {
                "sizing-mode": "proportional",
                "value": "1.0"
              },
              "height-constraints": {
                "sizing-mode": "proportional",
                "value": "1.0"
              }
            },
            "vector-content": "vector12.svg"
          },
          {
            "id": "Vector13",
            "margin": {
              "left": "6.121849060058594",
              "top": "13.347412109375",
              "right": "9.246208190917969",
              "bottom": "6.155387878417969"
            },
            "size-constraints": {
              "width-constraints": {
                "sizing-mode": "proportional",
                "value": "1.0"
              },
              "height-constraints": {
                "sizing-mode": "proportional",
                "value": "1.0"
              }
            },
            "vector-content": "vector13.svg"
          },
          {
            "id": "Group2",
            "margin": {
              "top": "0.0011663436889648438",
              "bottom": "0.00048542022705078125"
            },
            "is-structured": "false",
            "children": [
              "Vector14",
              "Vector15",
              "Vector16",
              "Vector17",
              "Vector18",
              "Vector19",
              "Vector20",
              "Vector21"
            ],
            "clip-content": "false"
          },
          {
            "id": "Vector14",
            "margin": {
              "left": "0.1641845703125",
              "bottom": "0.00015544891357421875"
            },
            "size-constraints": {
              "width-constraints": {
                "sizing-mode": "proportional",
                "value": "1.0"
              },
              "height-constraints": {
                "sizing-mode": "proportional",
                "value": "1.0"
              }
            },
            "vector-content": "vector14.svg"
          },
          {
            "id": "Vector15",
            "margin": {
              "left": "17.223480224609375",
              "top": "18.811113357543945",
              "right": "7.7737274169921875",
              "bottom": "8.59601879119873"
            },
            "size-constraints": {
              "width-constraints": {
                "sizing-mode": "proportional",
                "value": "1.0"
              },
              "height-constraints": {
                "sizing-mode": "proportional",
                "value": "1.0"
              }
            },
            "vector-content": "vector15.svg"
          },
          {
            "id": "Vector16",
            "margin": {
              "top": "18.494461059570312",
              "right": "8.251693725585938",
              "bottom": "5.988936424255371"
            },
            "size-constraints": {
              "width-constraints": {
                "sizing-mode": "proportional",
                "value": "1.0"
              },
              "height-constraints": {
                "sizing-mode": "proportional",
                "value": "1.0"
              }
            },
            "vector-content": "vector16.svg"
          },
          {
            "id": "Vector17",
            "margin": {
              "left": "9.703681945800781",
              "top": "11.389983177185059",
              "right": "13.675140380859375",
              "bottom": "13.591320991516113"
            },
            "size-constraints": {
              "width-constraints": {
                "sizing-mode": "proportional",
                "value": "1.0"
              },
              "height-constraints": {
                "sizing-mode": "proportional",
                "value": "1.0"
              }
            },
            "vector-content": "vector17.svg"
          },
          {
            "id": "Vector18",
            "margin": {
              "left": "9.703681945800781",
              "top": "11.389983177185059",
              "right": "15.1517333984375",
              "bottom": "23.65727138519287"
            },
            "size-constraints": {
              "width-constraints": {
                "sizing-mode": "proportional",
                "value": "1.0"
              },
              "height-constraints": {
                "sizing-mode": "proportional",
                "value": "1.0"
              }
            },
            "vector-content": "vector18.svg"
          },
          {
            "id": "Vector19",
            "margin": {
              "left": "6.4643402099609375",
              "top": "1.904245376586914",
              "right": "13.64471435546875",
              "bottom": "24.686238288879395"
            },
            "size-constraints": {
              "width-constraints": {
                "sizing-mode": "proportional",
                "value": "1.0"
              },
              "height-constraints": {
                "sizing-mode": "proportional",
                "value": "1.0"
              }
            },
            "vector-content": "vector19.svg"
          },
          {
            "id": "Vector20",
            "margin": {
              "left": "14.342842102050781",
              "top": "5.767682075500488",
              "right": "12.854782104492188",
              "bottom": "30.15117859840393"
            },
            "size-constraints": {
              "width-constraints": {
                "sizing-mode": "proportional",
                "value": "1.0"
              },
              "height-constraints": {
                "sizing-mode": "proportional",
                "value": "1.0"
              }
            },
            "vector-content": "vector20.svg"
          },
          {
            "id": "Vector21",
            "margin": {
              "left": "5.325042724609375",
              "top": "8.08531379699707",
              "right": "21.463790893554688",
              "bottom": "27.74229621887207"
            },
            "size-constraints": {
              "width-constraints": {
                "sizing-mode": "proportional",
                "value": "1.0"
              },
              "height-constraints": {
                "sizing-mode": "proportional",
                "value": "1.0"
              }
            },
            "vector-content": "vector21.svg"
          },
          {
            "id": "Vector22",
            "margin": {
              "top": "0.00119781494140625",
              "right": "1.3920364379882812",
              "bottom": "15.357734680175781"
            },
            "size-constraints": {
              "width-constraints": {
                "sizing-mode": "proportional",
                "value": "1.0"
              },
              "height-constraints": {
                "sizing-mode": "proportional",
                "value": "1.0"
              }
            },
            "vector-content": "vector22.svg"
          },
          {
            "id": "Group3",
            "margin": {
              "top": "2.2451171875"
            },
            "is-structured": "false",
            "children": [
              "Vector23",
              "Vector24",
              "Vector25",
              "Vector26",
              "Vector27"
            ],
            "clip-content": "false"
          },
          {
            "id": "Vector23",
            "margin": {
              "top": "17.231277465820312"
            },
            "size-constraints": {
              "width-constraints": {
                "sizing-mode": "proportional",
                "value": "1.0"
              },
              "height-constraints": {
                "sizing-mode": "proportional",
                "value": "1.0"
              }
            },
            "vector-content": "vector23.svg"
          },
          {
            "id": "Vector24",
            "margin": {
              "left": "5.47796630859375",
              "top": "11.553047180175781",
              "right": "6.88262939453125",
              "bottom": "10.150970458984375"
            },
            "size-constraints": {
              "width-constraints": {
                "sizing-mode": "proportional",
                "value": "1.0"
              },
              "height-constraints": {
                "sizing-mode": "proportional",
                "value": "1.0"
              }
            },
            "vector-content": "vector24.svg"
          },
          {
            "id": "Vector25",
            "margin": {
              "left": "5.928306579589844",
              "top": "11.553047180175781",
              "right": "7.6624298095703125",
              "bottom": "14.699378967285156"
            },
            "size-constraints": {
              "width-constraints": {
                "sizing-mode": "proportional",
                "value": "1.0"
              },
              "height-constraints": {
                "sizing-mode": "proportional",
                "value": "1.0"
              }
            },
            "vector-content": "vector25.svg"
          },
          {
            "id": "Vector26",
            "margin": {
              "left": "3.1591873168945312",
              "top": "5.4418182373046875",
              "right": "12.663970947265625",
              "bottom": "20.58880615234375"
            },
            "size-constraints": {
              "width-constraints": {
                "sizing-mode": "proportional",
                "value": "1.0"
              },
              "height-constraints": {
                "sizing-mode": "proportional",
                "value": "1.0"
              }
            },
            "vector-content": "vector26.svg"
          },
          {
            "id": "Vector27",
            "margin": {
              "left": "4.066314697265625",
              "right": "3.9900360107421875",
              "bottom": "15.97393798828125"
            },
            "size-constraints": {
              "width-constraints": {
                "sizing-mode": "proportional",
                "value": "1.0"
              },
              "height-constraints": {
                "sizing-mode": "proportional",
                "value": "1.0"
              }
            },
            "vector-content": "vector27.svg"
          },
          {
            "id": "Vector28",
            "margin": {
              "top": "14.979171752929688",
              "right": "13.350830078125",
              "bottom": "4.2291107177734375"
            },
            "size-constraints": {
              "width-constraints": {
                "sizing-mode": "proportional",
                "value": "1.0"
              },
              "height-constraints": {
                "sizing-mode": "proportional",
                "value": "1.0"
              }
            },
            "vector-content": "vector28.svg"
          },
          {
            "id": "Vector29",
            "margin": {
              "left": "1.7648162841796875",
              "top": "14.547866821289062",
              "right": "5.910423278808594"
            },
            "size-constraints": {
              "width-constraints": {
                "sizing-mode": "proportional",
                "value": "1.0"
              },
              "height-constraints": {
                "sizing-mode": "proportional",
                "value": "1.0"
              }
            },
            "vector-content": "vector29.svg"
          },
          {
            "id": "Vector30",
            "margin": {
              "left": "6.050804138183594",
              "top": "9.817459106445312",
              "right": "10.815719604492188",
              "bottom": "9.85491943359375"
            },
            "size-constraints": {
              "width-constraints": {
                "sizing-mode": "proportional",
                "value": "1.0"
              },
              "height-constraints": {
                "sizing-mode": "proportional",
                "value": "1.0"
              }
            },
            "vector-content": "vector30.svg"
          },
          {
            "id": "Vector31",
            "margin": {
              "left": "4.519386291503906",
              "top": "1.8095245361328125",
              "right": "10.631965637207031",
              "bottom": "18.230545043945312"
            },
            "size-constraints": {
              "width-constraints": {
                "sizing-mode": "proportional",
                "value": "1.0"
              },
              "height-constraints": {
                "sizing-mode": "proportional",
                "value": "1.0"
              }
            },
            "vector-content": "vector31.svg"
          },
          {
            "id": "Vector32",
            "margin": {
              "left": "5.618247985839844",
              "right": "7.859779357910156",
              "bottom": "18.141204833984375"
            },
            "size-constraints": {
              "width-constraints": {
                "sizing-mode": "proportional",
                "value": "1.0"
              },
              "height-constraints": {
                "sizing-mode": "proportional",
                "value": "1.0"
              }
            },
            "vector-content": "vector32.svg"
          },
          {
            "id": "Vector33",
            "margin": {
              "left": "12.477333068847656",
              "top": "15.346298217773438",
              "right": "0.0141754150390625",
              "bottom": "2.4279632568359375"
            },
            "size-constraints": {
              "width-constraints": {
                "sizing-mode": "proportional",
                "value": "1.0"
              },
              "height-constraints": {
                "sizing-mode": "proportional",
                "value": "1.0"
              }
            },
            "vector-content": "vector33.svg"
          },
          {
            "id": "Ellipse 10",
            "size-constraints": {
              "width-constraints": {
                "sizing-mode": "proportional",
                "value": "1.0"
              },
              "height-constraints": {
                "sizing-mode": "proportional",
                "value": "1.0"
              }
            },
            "vector-content": "ellipse_7.svg"
          },
          {
            "id": "Frame5",
            "margin": {
              "left": "10.855255126953125",
              "top": "4.9342041015625",
              "right": "10.733558654785156",
              "bottom": "5.10198974609375"
            },
            "is-structured": "false",
            "children": [
              "Vector34",
              "Vector35",
              "Vector36",
              "Group4",
              "Vector37"
            ]
          },
          {
            "id": "Vector34",
            "margin": {
              "left": "3.763153076171875",
              "top": "21.284393310546875",
              "right": "0.00000762939453125"
            },
            "size-constraints": {
              "width-constraints": {
                "sizing-mode": "proportional",
                "value": "1.0"
              },
              "height-constraints": {
                "sizing-mode": "proportional",
                "value": "1.0"
              }
            },
            "vector-content": "vector34.svg"
          },
          {
            "id": "Vector35",
            "margin": {
              "left": "14.049346923828125",
              "top": "14.626434326171875",
              "right": "7.710426330566406",
              "bottom": "14.173858642578125"
            },
            "size-constraints": {
              "width-constraints": {
                "sizing-mode": "proportional",
                "value": "1.0"
              },
              "height-constraints": {
                "sizing-mode": "proportional",
                "value": "1.0"
              }
            },
            "vector-content": "vector35.svg"
          },
          {
            "id": "Vector36",
            "margin": {
              "left": "14.963821411132812",
              "top": "14.62506103515625",
              "right": "8.319068908691406",
              "bottom": "21.384857177734375"
            },
            "size-constraints": {
              "width-constraints": {
                "sizing-mode": "proportional",
                "value": "1.0"
              },
              "height-constraints": {
                "sizing-mode": "proportional",
                "value": "1.0"
              }
            },
            "vector-content": "vector36.svg"
          },
          {
            "id": "Group4",
            "margin": {
              "left": "10.010787963867188",
              "right": "5.305961608886719",
              "bottom": "22.437469482421875"
            },
            "is-structured": "false",
            "children": [
              "Vector38",
              "Vector39",
              "Vector40"
            ],
            "clip-content": "false"
          },
          {
            "id": "Vector37",
            "margin": {
              "top": "22.876495361328125",
              "right": "17.64928436279297",
              "bottom": "1.914459228515625"
            },
            "size-constraints": {
              "width-constraints": {
                "sizing-mode": "proportional",
                "value": "1.0"
              },
              "height-constraints": {
                "sizing-mode": "proportional",
                "value": "1.0"
              }
            },
            "vector-content": "vector37.svg"
          },
          {
            "id": "Vector38",
            "margin": {
              "left": "3.780120849609375",
              "top": "3.455810546875",
              "right": "0.0000152587890625",
              "bottom": "0.167083740234375"
            },
            "size-constraints": {
              "width-constraints": {
                "sizing-mode": "proportional",
                "value": "1.0"
              },
              "height-constraints": {
                "sizing-mode": "proportional",
                "value": "1.0"
              }
            },
            "vector-content": "vector38.svg"
          },
          {
            "id": "Vector39",
            "margin": {
              "right": "1.091583251953125"
            },
            "size-constraints": {
              "width-constraints": {
                "sizing-mode": "proportional",
                "value": "1.0"
              },
              "height-constraints": {
                "sizing-mode": "proportional",
                "value": "1.0"
              }
            },
            "vector-content": "vector39.svg"
          },
          {
            "id": "Vector40",
            "margin": {
              "left": "4.436126708984375",
              "top": "9.672027587890625",
              "right": "6.7001495361328125",
              "bottom": "4.46044921875"
            },
            "size-constraints": {
              "width-constraints": {
                "sizing-mode": "proportional",
                "value": "1.0"
              },
              "height-constraints": {
                "sizing-mode": "proportional",
                "value": "1.0"
              }
            },
            "vector-content": "vector40.svg"
          }
        ]
      }
    }
  },
  "previews": [
    {
      "design": "Component 8",
      "size": {
        "width": 363.9998779296875,
        "height": 586.0
      }
    }
  ],
  "adin-component-search-paths": [],
  "image-search-paths": [],
  "vector-search-paths": []
}